concealment/__init__.py
concealment/nothin.py
concealment-0.0.3.dist-info/LICENSE
concealment-0.0.3.dist-info/METADATA
concealment-0.0.3.dist-info/WHEEL
concealment-0.0.3.dist-info/top_level.txt
concealment-0.0.3.dist-info/RECORD
